astrojs_aws/construct/__init__.py
astrojs_aws/construct/py.typed
astrojs_aws/construct/_jsii/__init__.py
astrojs_aws/construct/_jsii/construct@0.0.20.jsii.tgz
astrojs_aws.construct-0.0.20.dist-info/LICENSE
astrojs_aws.construct-0.0.20.dist-info/METADATA
astrojs_aws.construct-0.0.20.dist-info/WHEEL
astrojs_aws.construct-0.0.20.dist-info/top_level.txt
astrojs_aws.construct-0.0.20.dist-info/RECORD
