Metadata-Version: 2.1
Name: astrojs-aws.construct
Version: 0.0.20
Summary: The CDK Construct Library of Astro
Home-page: https://github.com/helbing/astrojs-aws/tree/main/packages/construct
Author: helbing
License: MIT
Project-URL: Source, https://github.com/helbing/astrojs-aws.git
Classifier: Intended Audience :: Developers
Classifier: Operating System :: OS Independent
Classifier: Programming Language :: JavaScript
Classifier: Programming Language :: Python :: 3 :: Only
Classifier: Programming Language :: Python :: 3.7
Classifier: Programming Language :: Python :: 3.8
Classifier: Programming Language :: Python :: 3.9
Classifier: Programming Language :: Python :: 3.10
Classifier: Programming Language :: Python :: 3.11
Classifier: Typing :: Typed
Classifier: Development Status :: 4 - Beta
Classifier: License :: OSI Approved
Requires-Python: ~=3.7
License-File: LICENSE
Requires-Dist: aws-cdk-lib (==2.79.1)
Requires-Dist: aws-cdk.aws-apigatewayv2-alpha (==2.79.1.a0)
Requires-Dist: aws-cdk.aws-apigatewayv2-integrations-alpha (==2.79.1.a0)
Requires-Dist: constructs (==10.2.27)
Requires-Dist: jsii (<2.0.0,>=1.80.0)
Requires-Dist: publication (>=0.0.3)
Requires-Dist: typeguard (~=2.13.3)
